<OBJECT ID="1" CLASS="CL-PREVALENCE::TRANSACTION"><SLOT NAME="CL-PREVALENCE::ARGS"><SEQUENCE ID="2" CLASS="CL:LIST" SIZE="1"><OBJECT ID="3" CLASS="FILETREE::DRIVE"><SLOT NAME="WEBLOCKS::ID"><INT>0</INT></SLOT><SLOT NAME="FILETREE::NAME"><STRING>aaa</STRING></SLOT><SLOT NAME="FILETREE::DESCRIPTION"><NULL/></SLOT><SLOT NAME="FILETREE::FOLDERS"><NULL/></SLOT><SLOT NAME="FILETREE::FILES"><NULL/></SLOT></OBJECT></SEQUENCE></SLOT><SLOT NAME="CL:FUNCTION"><SYMBOL>WEBLOCKS-PREVALENCE::TX-PERSIST-OBJECT-PREVALENCE</SYMBOL></SLOT></OBJECT>
<OBJECT ID="1" CLASS="CL-PREVALENCE::TRANSACTION"><SLOT NAME="CL-PREVALENCE::ARGS"><SEQUENCE ID="2" CLASS="CL:LIST" SIZE="1"><OBJECT ID="3" CLASS="FILETREE::DRIVE"><SLOT NAME="WEBLOCKS::ID"><INT>0</INT></SLOT><SLOT NAME="FILETREE::NAME"><STRING>aaa</STRING></SLOT><SLOT NAME="FILETREE::DESCRIPTION"><NULL/></SLOT><SLOT NAME="FILETREE::FOLDERS"><NULL/></SLOT><SLOT NAME="FILETREE::FILES"><NULL/></SLOT></OBJECT></SEQUENCE></SLOT><SLOT NAME="CL:FUNCTION"><SYMBOL>WEBLOCKS-PREVALENCE::TX-PERSIST-OBJECT-PREVALENCE</SYMBOL></SLOT></OBJECT>
<OBJECT ID="1" CLASS="CL-PREVALENCE::TRANSACTION"><SLOT NAME="CL-PREVALENCE::ARGS"><SEQUENCE ID="2" CLASS="CL:LIST" SIZE="1"><OBJECT ID="3" CLASS="FILETREE::DRIVE"><SLOT NAME="WEBLOCKS::ID"><INT>0</INT></SLOT><SLOT NAME="FILETREE::NAME"><STRING>aaa</STRING></SLOT><SLOT NAME="FILETREE::DESCRIPTION"><NULL/></SLOT><SLOT NAME="FILETREE::FOLDERS"><NULL/></SLOT><SLOT NAME="FILETREE::FILES"><NULL/></SLOT></OBJECT></SEQUENCE></SLOT><SLOT NAME="CL:FUNCTION"><SYMBOL>WEBLOCKS-PREVALENCE::TX-PERSIST-OBJECT-PREVALENCE</SYMBOL></SLOT></OBJECT>
<OBJECT ID="1" CLASS="CL-PREVALENCE::TRANSACTION"><SLOT NAME="CL-PREVALENCE::ARGS"><SEQUENCE ID="2" CLASS="CL:LIST" SIZE="2"><SYMBOL>FILETREE::DRIVE</SYMBOL><INT>0</INT></SEQUENCE></SLOT><SLOT NAME="CL:FUNCTION"><SYMBOL>WEBLOCKS-PREVALENCE::TX-DELETE-OBJECT-BY-ID-PREVALENCE</SYMBOL></SLOT></OBJECT>
<OBJECT ID="1" CLASS="CL-PREVALENCE::TRANSACTION"><SLOT NAME="CL-PREVALENCE::ARGS"><SEQUENCE ID="2" CLASS="CL:LIST" SIZE="1"><OBJECT ID="3" CLASS="FILETREE::DRIVE"><SLOT NAME="WEBLOCKS::ID"><INT>0</INT></SLOT><SLOT NAME="FILETREE::NAME"><STRING>Drive1</STRING></SLOT><SLOT NAME="FILETREE::DESCRIPTION"><NULL/></SLOT><SLOT NAME="FILETREE::FOLDERS"><NULL/></SLOT><SLOT NAME="FILETREE::FILES"><NULL/></SLOT></OBJECT></SEQUENCE></SLOT><SLOT NAME="CL:FUNCTION"><SYMBOL>WEBLOCKS-PREVALENCE::TX-PERSIST-OBJECT-PREVALENCE</SYMBOL></SLOT></OBJECT>
<OBJECT ID="1" CLASS="CL-PREVALENCE::TRANSACTION"><SLOT NAME="CL-PREVALENCE::ARGS"><SEQUENCE ID="2" CLASS="CL:LIST" SIZE="1"><OBJECT ID="3" CLASS="FILETREE::DRIVE"><SLOT NAME="WEBLOCKS::ID"><INT>0</INT></SLOT><SLOT NAME="FILETREE::NAME"><STRING>Drive1</STRING></SLOT><SLOT NAME="FILETREE::DESCRIPTION"><NULL/></SLOT><SLOT NAME="FILETREE::FOLDERS"><NULL/></SLOT><SLOT NAME="FILETREE::FILES"><NULL/></SLOT></OBJECT></SEQUENCE></SLOT><SLOT NAME="CL:FUNCTION"><SYMBOL>WEBLOCKS-PREVALENCE::TX-PERSIST-OBJECT-PREVALENCE</SYMBOL></SLOT></OBJECT>
<OBJECT ID="1" CLASS="CL-PREVALENCE::TRANSACTION"><SLOT NAME="CL-PREVALENCE::ARGS"><SEQUENCE ID="2" CLASS="CL:LIST" SIZE="1"><OBJECT ID="3" CLASS="FILETREE::DRIVE"><SLOT NAME="WEBLOCKS::ID"><INT>1</INT></SLOT><SLOT NAME="FILETREE::NAME"><STRING>Drive2</STRING></SLOT><SLOT NAME="FILETREE::DESCRIPTION"><NULL/></SLOT><SLOT NAME="FILETREE::FOLDERS"><NULL/></SLOT><SLOT NAME="FILETREE::FILES"><NULL/></SLOT></OBJECT></SEQUENCE></SLOT><SLOT NAME="CL:FUNCTION"><SYMBOL>WEBLOCKS-PREVALENCE::TX-PERSIST-OBJECT-PREVALENCE</SYMBOL></SLOT></OBJECT>
<OBJECT ID="1" CLASS="CL-PREVALENCE::TRANSACTION"><SLOT NAME="CL-PREVALENCE::ARGS"><SEQUENCE ID="2" CLASS="CL:LIST" SIZE="1"><OBJECT ID="3" CLASS="FILETREE::FOLDER"><SLOT NAME="WEBLOCKS::ID"><INT>0</INT></SLOT><SLOT NAME="FILETREE::NAME"><STRING>folder1</STRING></SLOT><SLOT NAME="FILETREE::DESCRIPTION"><NULL/></SLOT><SLOT NAME="FILETREE::FOLDERS"><NULL/></SLOT><SLOT NAME="FILETREE::FILES"><NULL/></SLOT></OBJECT></SEQUENCE></SLOT><SLOT NAME="CL:FUNCTION"><SYMBOL>WEBLOCKS-PREVALENCE::TX-PERSIST-OBJECT-PREVALENCE</SYMBOL></SLOT></OBJECT>
